cli_gitpage/__init__.py
cli_gitpage/cli.py
cli_gitpage-0.1.dist-info/METADATA
cli_gitpage-0.1.dist-info/WHEEL
cli_gitpage-0.1.dist-info/entry_points.txt
cli_gitpage-0.1.dist-info/top_level.txt
cli_gitpage-0.1.dist-info/RECORD
