Metadata-Version: 2.1
Name: cli-gitpage
Version: 0.1
Requires-Dist: click
